nicebuilder/__init__.py
nicebuilder-0.6.0.dist-info/METADATA
nicebuilder-0.6.0.dist-info/WHEEL
nicebuilder-0.6.0.dist-info/RECORD
