Metadata-Version: 2.3
Name: nicebuilder
Version: 0.6.0
Summary: Tiny framework for building NiceGUI applications
Author-email: Masuda Shinsuke <shinsuke.masuda@gmail.com>
Requires-Python: >=3.8
Requires-Dist: nicegui>=1.4.19
